{
  "updated_at": "2026-06-27T17:29:29.699937+00:00",
  "source_file": "C:\\_lavoro\\2026\\GTWC\\Events\\260628_E04_24h_Spa\\260628_GTWC_24h_Spa.xlsm",
  "sheet_name": "24h stints",
  "stints": [
    {
      "stint": 1,
      "driver": "1-SB",
      "start": "16:30:00",
      "end": "17:30:00",
      "ready": ""
    },
    {
      "stint": 2,
      "driver": "3-KP",
      "start": "17:32:48",
      "end": "18:35:36",
      "ready": ""
    },
    {
      "stint": 3,
      "driver": "2-AD",
      "start": "18:34:44",
      "end": "19:34:44",
      "ready": "17:04:44"
    },
    {
      "stint": 4,
      "driver": "4-OS",
      "start": "19:36:40",
      "end": "20:36:40",
      "ready": "18:06:40"
    },
    {
      "stint": 5,
      "driver": "3-KP",
      "start": "20:38:36",
      "end": "21:38:36",
      "ready": "19:08:36"
    },
    {
      "stint": 6,
      "driver": "3-KP",
      "start": "21:40:32",
      "end": "22:40:32",
      "ready": ""
    },
    {
      "stint": 7,
      "driver": "1-SB",
      "start": "22:42:28",
      "end": "23:42:28",
      "ready": "21:12:28"
    },
    {
      "stint": 8,
      "driver": "1-SB",
      "start": "23:44:24",
      "end": "00:44:24",
      "ready": ""
    },
    {
      "stint": 9,
      "driver": "4-OS",
      "start": "00:46:20",
      "end": "01:46:20",
      "ready": "23:16:20"
    },
    {
      "stint": 10,
      "driver": "4-OS",
      "start": "01:48:16",
      "end": "02:48:16",
      "ready": ""
    },
    {
      "stint": 11,
      "driver": "3-KP",
      "start": "02:50:12",
      "end": "03:50:12",
      "ready": "01:20:12"
    },
    {
      "stint": 12,
      "driver": "3-KP",
      "start": "03:52:08",
      "end": "04:52:08",
      "ready": ""
    },
    {
      "stint": 13,
      "driver": "1-SB",
      "start": "04:54:04",
      "end": "05:54:04",
      "ready": "03:24:04"
    },
    {
      "stint": 14,
      "driver": "1-SB",
      "start": "05:56:00",
      "end": "06:56:00",
      "ready": ""
    },
    {
      "stint": 15,
      "driver": "2-AD",
      "start": "06:57:56",
      "end": "07:57:56",
      "ready": "05:27:56"
    },
    {
      "stint": 16,
      "driver": "2-AD",
      "start": "07:59:52",
      "end": "08:59:52",
      "ready": ""
    },
    {
      "stint": 17,
      "driver": "4-OS",
      "start": "09:01:48",
      "end": "10:01:48",
      "ready": "07:31:48"
    },
    {
      "stint": 18,
      "driver": "4-OS",
      "start": "10:03:44",
      "end": "11:03:44",
      "ready": ""
    },
    {
      "stint": 19,
      "driver": "3-KP",
      "start": "11:05:40",
      "end": "12:05:40",
      "ready": "09:35:40"
    },
    {
      "stint": 20,
      "driver": "1-SB",
      "start": "12:07:36",
      "end": "13:07:36",
      "ready": "10:37:36"
    },
    {
      "stint": 21,
      "driver": "2-AD",
      "start": "13:09:32",
      "end": "14:09:32",
      "ready": "11:39:32"
    },
    {
      "stint": 22,
      "driver": "4-OS",
      "start": "14:11:28",
      "end": "15:11:28",
      "ready": "12:41:28"
    },
    {
      "stint": 23,
      "driver": "3-KP",
      "start": "15:13:24",
      "end": "16:13:24",
      "ready": "13:43:24"
    },
    {
      "stint": 24,
      "driver": "",
      "start": "",
      "end": "",
      "ready": ""
    }
  ]
}