{
  "updated_at": "2026-06-27T18:16:30.369870+00:00",
  "source_file": "C:\\_lavoro\\2026\\GTWC\\Events\\260628_E04_24h_Spa\\260628_GTWC_24h_Spa.xlsm",
  "sheet_name": "24h stints",
  "stints": [
    {
      "stint": 1,
      "driver": "1-SB",
      "start": "16:30:00",
      "end": "17:30:00",
      "ready": ""
    },
    {
      "stint": 2,
      "driver": "3-KP",
      "start": "17:32:48",
      "end": "18:35:36",
      "ready": ""
    },
    {
      "stint": 3,
      "driver": "2-AD",
      "start": "18:37:41",
      "end": "19:42:35",
      "ready": "17:07:41"
    },
    {
      "stint": 4,
      "driver": "4-OS",
      "start": "19:39:37",
      "end": "20:39:37",
      "ready": "18:09:37"
    },
    {
      "stint": 5,
      "driver": "3-KP",
      "start": "20:41:33",
      "end": "21:41:33",
      "ready": "19:11:33"
    },
    {
      "stint": 6,
      "driver": "3-KP",
      "start": "21:43:29",
      "end": "22:43:29",
      "ready": ""
    },
    {
      "stint": 7,
      "driver": "1-SB",
      "start": "22:45:25",
      "end": "23:45:25",
      "ready": "21:15:25"
    },
    {
      "stint": 8,
      "driver": "1-SB",
      "start": "23:47:21",
      "end": "00:47:21",
      "ready": ""
    },
    {
      "stint": 9,
      "driver": "4-OS",
      "start": "00:49:17",
      "end": "01:49:17",
      "ready": "23:19:17"
    },
    {
      "stint": 10,
      "driver": "4-OS",
      "start": "01:51:13",
      "end": "02:51:13",
      "ready": ""
    },
    {
      "stint": 11,
      "driver": "3-KP",
      "start": "02:53:09",
      "end": "03:53:09",
      "ready": "01:23:09"
    },
    {
      "stint": 12,
      "driver": "3-KP",
      "start": "03:55:05",
      "end": "04:55:05",
      "ready": ""
    },
    {
      "stint": 13,
      "driver": "1-SB",
      "start": "04:57:01",
      "end": "05:57:01",
      "ready": "03:27:01"
    },
    {
      "stint": 14,
      "driver": "1-SB",
      "start": "05:58:57",
      "end": "06:58:57",
      "ready": ""
    },
    {
      "stint": 15,
      "driver": "2-AD",
      "start": "07:00:53",
      "end": "08:00:53",
      "ready": "05:30:53"
    },
    {
      "stint": 16,
      "driver": "2-AD",
      "start": "08:02:49",
      "end": "09:02:49",
      "ready": ""
    },
    {
      "stint": 17,
      "driver": "4-OS",
      "start": "09:04:45",
      "end": "10:04:45",
      "ready": "07:34:45"
    },
    {
      "stint": 18,
      "driver": "4-OS",
      "start": "10:06:41",
      "end": "11:06:41",
      "ready": ""
    },
    {
      "stint": 19,
      "driver": "3-KP",
      "start": "11:08:37",
      "end": "12:08:37",
      "ready": "09:38:37"
    },
    {
      "stint": 20,
      "driver": "1-SB",
      "start": "12:10:33",
      "end": "13:10:33",
      "ready": "10:40:33"
    },
    {
      "stint": 21,
      "driver": "2-AD",
      "start": "13:12:29",
      "end": "14:12:29",
      "ready": "11:42:29"
    },
    {
      "stint": 22,
      "driver": "4-OS",
      "start": "14:14:25",
      "end": "15:14:25",
      "ready": "12:44:25"
    },
    {
      "stint": 23,
      "driver": "3-KP",
      "start": "15:16:21",
      "end": "16:16:21",
      "ready": "13:46:21"
    },
    {
      "stint": 24,
      "driver": "",
      "start": "",
      "end": "",
      "ready": ""
    }
  ]
}