{
  "updated_at": "2026-07-01T08:35:00.983893+00:00",
  "source_file": "C:\\_lavoro\\2026\\DTM\\Events\\260704_DTM04_Norisring\\260705_DTM04_Norisring.xlsm",
  "sheet_name": "24h stints",
  "rows": [
    {
      "stint": 1,
      "start": "11:30:00",
      "end": "11:48:11",
      "tyre_set": "#07-T04-17",
      "in_the_hoven": "",
      "mounted": "",
      "rim_temp": "",
      "FL": "0.82",
      "FR": "0.82",
      "RL": "0.79",
      "RR": "0.79",
      "track_temp": "30",
      "bleed": "",
      "excel_row": 2
    },
    {
      "stint": 2,
      "start": "11:48:11",
      "end": "12:03:06",
      "tyre_set": "#07-T04-17",
      "in_the_hoven": "",
      "mounted": "",
      "rim_temp": "",
      "FL": "",
      "FR": "",
      "RL": "",
      "RR": "",
      "track_temp": "30",
      "bleed": "",
      "excel_row": 3
    },
    {
      "stint": 3,
      "start": "12:03:06",
      "end": "12:17:02",
      "tyre_set": "#07-D03-19",
      "in_the_hoven": "",
      "mounted": "",
      "rim_temp": "",
      "FL": "",
      "FR": "",
      "RL": "",
      "RR": "",
      "track_temp": "30",
      "bleed": "",
      "excel_row": 4
    },
    {
      "stint": 4,
      "start": "",
      "end": "",
      "tyre_set": "",
      "in_the_hoven": "",
      "mounted": "",
      "rim_temp": "",
      "FL": "",
      "FR": "",
      "RL": "",
      "RR": "",
      "track_temp": "",
      "bleed": "",
      "excel_row": 5
    },
    {
      "stint": 1,
      "start": "16:00:00",
      "end": "16:04:34",
      "tyre_set": "#07-T04-17",
      "in_the_hoven": "",
      "mounted": "",
      "rim_temp": "",
      "FL": "",
      "FR": "",
      "RL": "",
      "RR": "",
      "track_temp": "",
      "bleed": "",
      "excel_row": 6
    },
    {
      "stint": 2,
      "start": "16:04:34",
      "end": "16:22:45",
      "tyre_set": "#07-D03-19",
      "in_the_hoven": "",
      "mounted": "",
      "rim_temp": "",
      "FL": "",
      "FR": "",
      "RL": "",
      "RR": "",
      "track_temp": "",
      "bleed": "",
      "excel_row": 7
    },
    {
      "stint": 3,
      "start": "16:22:45",
      "end": "16:29:31",
      "tyre_set": "#07-D04-23",
      "in_the_hoven": "",
      "mounted": "",
      "rim_temp": "",
      "FL": "",
      "FR": "",
      "RL": "",
      "RR": "",
      "track_temp": "",
      "bleed": "",
      "excel_row": 8
    },
    {
      "stint": 4,
      "start": "16:29:31",
      "end": "16:42:42",
      "tyre_set": "#07-D04-23",
      "in_the_hoven": "",
      "mounted": "",
      "rim_temp": "",
      "FL": "",
      "FR": "",
      "RL": "",
      "RR": "",
      "track_temp": "",
      "bleed": "",
      "excel_row": 9
    },
    {
      "stint": 1,
      "start": "09:35:00",
      "end": "09:38:45",
      "tyre_set": "#07-D04-24",
      "in_the_hoven": "",
      "mounted": "",
      "rim_temp": "",
      "FL": "",
      "FR": "",
      "RL": "",
      "RR": "",
      "track_temp": "",
      "bleed": "",
      "excel_row": 11
    },
    {
      "stint": 2,
      "start": "09:38:45",
      "end": "09:42:30",
      "tyre_set": "#07-D04-24",
      "in_the_hoven": "",
      "mounted": "",
      "rim_temp": "",
      "FL": "",
      "FR": "",
      "RL": "",
      "RR": "",
      "track_temp": "",
      "bleed": "",
      "excel_row": 12
    },
    {
      "stint": 1,
      "start": "16:30:00",
      "end": "17:30:00",
      "tyre_set": "",
      "in_the_hoven": "",
      "mounted": "",
      "rim_temp": "",
      "FL": "",
      "FR": "",
      "RL": "",
      "RR": "",
      "track_temp": "",
      "bleed": "",
      "excel_row": 14
    },
    {
      "stint": 2,
      "start": "17:32:48",
      "end": "18:32:48",
      "tyre_set": "",
      "in_the_hoven": "",
      "mounted": "",
      "rim_temp": "",
      "FL": "",
      "FR": "",
      "RL": "",
      "RR": "",
      "track_temp": "",
      "bleed": "",
      "excel_row": 15
    },
    {
      "stint": 3,
      "start": "18:37:41",
      "end": "19:37:41",
      "tyre_set": "",
      "in_the_hoven": "",
      "mounted": "",
      "rim_temp": "",
      "FL": "",
      "FR": "",
      "RL": "",
      "RR": "",
      "track_temp": "",
      "bleed": "",
      "excel_row": 16
    },
    {
      "stint": 4,
      "start": "19:43:52",
      "end": "20:43:52",
      "tyre_set": "",
      "in_the_hoven": "",
      "mounted": "",
      "rim_temp": "",
      "FL": "",
      "FR": "",
      "RL": "",
      "RR": "",
      "track_temp": "",
      "bleed": "",
      "excel_row": 17
    },
    {
      "stint": 5,
      "start": "19:55:02",
      "end": "20:55:02",
      "tyre_set": "",
      "in_the_hoven": "",
      "mounted": "",
      "rim_temp": "",
      "FL": "",
      "FR": "",
      "RL": "",
      "RR": "",
      "track_temp": "",
      "bleed": "",
      "excel_row": 18
    },
    {
      "stint": 6,
      "start": "20:45:24",
      "end": "21:45:24",
      "tyre_set": "",
      "in_the_hoven": "",
      "mounted": "",
      "rim_temp": "",
      "FL": "",
      "FR": "",
      "RL": "",
      "RR": "",
      "track_temp": "",
      "bleed": "",
      "excel_row": 19
    },
    {
      "stint": 7,
      "start": "21:45:58",
      "end": "22:45:58",
      "tyre_set": "",
      "in_the_hoven": "",
      "mounted": "",
      "rim_temp": "",
      "FL": "",
      "FR": "",
      "RL": "",
      "RR": "",
      "track_temp": "",
      "bleed": "",
      "excel_row": 20
    },
    {
      "stint": 8,
      "start": "22:47:54",
      "end": "23:47:54",
      "tyre_set": "",
      "in_the_hoven": "",
      "mounted": "",
      "rim_temp": "",
      "FL": "",
      "FR": "",
      "RL": "",
      "RR": "",
      "track_temp": "",
      "bleed": "",
      "excel_row": 21
    },
    {
      "stint": 9,
      "start": "23:49:50",
      "end": "00:49:50",
      "tyre_set": "",
      "in_the_hoven": "",
      "mounted": "",
      "rim_temp": "",
      "FL": "",
      "FR": "",
      "RL": "",
      "RR": "",
      "track_temp": "",
      "bleed": "",
      "excel_row": 22
    },
    {
      "stint": 10,
      "start": "00:51:46",
      "end": "01:51:46",
      "tyre_set": "",
      "in_the_hoven": "",
      "mounted": "",
      "rim_temp": "",
      "FL": "",
      "FR": "",
      "RL": "",
      "RR": "",
      "track_temp": "",
      "bleed": "",
      "excel_row": 23
    },
    {
      "stint": 11,
      "start": "01:53:42",
      "end": "02:53:42",
      "tyre_set": "",
      "in_the_hoven": "",
      "mounted": "",
      "rim_temp": "",
      "FL": "",
      "FR": "",
      "RL": "",
      "RR": "",
      "track_temp": "",
      "bleed": "",
      "excel_row": 24
    },
    {
      "stint": 12,
      "start": "",
      "end": "",
      "tyre_set": "",
      "in_the_hoven": "",
      "mounted": "",
      "rim_temp": "",
      "FL": "",
      "FR": "",
      "RL": "",
      "RR": "",
      "track_temp": "",
      "bleed": "",
      "excel_row": 25
    }
  ]
}